clcomuna
